bootstrap4_datetime/__init__.py
bootstrap4_datetime/widgets.py
bootstrap4_datetime/static/bootstrap4_datetime/css/bootstrap-datetimepicker.css
bootstrap4_datetime/static/bootstrap4_datetime/css/bootstrap-datetimepicker.min.css
bootstrap4_datetime/static/bootstrap4_datetime/js/bootstrap-datetimepicker.js
bootstrap4_datetime/static/bootstrap4_datetime/js/bootstrap-datetimepicker.min.js
bootstrap4_datetime/static/bootstrap4_datetime/js/bootstrap-datetimepicker.min.min.js
bootstrap4_datetime/static/bootstrap4_datetime/js/moment.min.js
bootstrap4_datetime/static/bootstrap4_datetime/js/locales/bootstrap-datetimepicker.ar-ma.js
bootstrap4_datetime/static/bootstrap4_datetime/js/locales/bootstrap-datetimepicker.ar.js
bootstrap4_datetime/static/bootstrap4_datetime/js/locales/bootstrap-datetimepicker.bg.js
bootstrap4_datetime/static/bootstrap4_datetime/js/locales/bootstrap-datetimepicker.br.js
bootstrap4_datetime/static/bootstrap4_datetime/js/locales/bootstrap-datetimepicker.bs.js
bootstrap4_datetime/static/bootstrap4_datetime/js/locales/bootstrap-datetimepicker.by.js
bootstrap4_datetime/static/bootstrap4_datetime/js/locales/bootstrap-datetimepicker.ca.js
bootstrap4_datetime/static/bootstrap4_datetime/js/locales/bootstrap-datetimepicker.cs.js
bootstrap4_datetime/static/bootstrap4_datetime/js/locales/bootstrap-datetimepicker.cv.js
bootstrap4_datetime/static/bootstrap4_datetime/js/locales/bootstrap-datetimepicker.da.js
bootstrap4_datetime/static/bootstrap4_datetime/js/locales/bootstrap-datetimepicker.de.js
bootstrap4_datetime/static/bootstrap4_datetime/js/locales/bootstrap-datetimepicker.el.js
bootstrap4_datetime/static/bootstrap4_datetime/js/locales/bootstrap-datetimepicker.en-au.js
bootstrap4_datetime/static/bootstrap4_datetime/js/locales/bootstrap-datetimepicker.en-ca.js
bootstrap4_datetime/static/bootstrap4_datetime/js/locales/bootstrap-datetimepicker.en-gb.js
bootstrap4_datetime/static/bootstrap4_datetime/js/locales/bootstrap-datetimepicker.eo.js
django_bootstrap4_datetimepicker-4.2.dist-info/DESCRIPTION.rst
django_bootstrap4_datetimepicker-4.2.dist-info/METADATA
django_bootstrap4_datetimepicker-4.2.dist-info/RECORD
django_bootstrap4_datetimepicker-4.2.dist-info/WHEEL
django_bootstrap4_datetimepicker-4.2.dist-info/metadata.json
django_bootstrap4_datetimepicker-4.2.dist-info/top_level.txt
