Metadata-Version: 1.1
Name: django-bootstrap4-datetimepicker
Version: 4.2
Summary: Bootstrap4 compatible datetimepicker for Django projects.
Home-page: https://github.com/pattyjogal/django-bootstrap4-datetimepicker.git
Author: Patrick Gallagher
Author-email: patrickj@cpgallagher.com
License: Apache License 2.0
Platform: UNKNOWN
Classifier: Intended Audience :: Developers
Classifier: License :: OSI Approved :: Apache Software License
Classifier: Programming Language :: Python
Classifier: Programming Language :: Python :: 2
Classifier: Programming Language :: Python :: 3
Classifier: Operating System :: OS Independent
Classifier: Topic :: Software Development :: Libraries
Classifier: Topic :: Utilities
Classifier: Environment :: Web Environment
Classifier: Framework :: Django
